
{
    "region" : "us-east-2",
    "configuration" : "Debug",
    "framework"     : "netcoreapp2.2",
    "self-contained" : true,
    "application"    : "FastdoSysBackEndv2",
    "environment"    : "Fastdosysbackendv2-env",
    "enable-xray"    : false,
    "enhanced-health-type" : "enhanced",
    "additional-options"   : "",
    "solution-stack"       : "64bit Amazon Linux 2 v1.0.0 running .NET Core",
    "environment-type"     : "SingleInstance",
    "cname"                : "fastdobackendsysprod",
    "instance-type"        : "t3a.medium",
    "key-pair"             : "",
    "instance-profile"     : "aws-elasticbeanstalk-ec2-role",
    "service-role"         : "aws-elasticbeanstalk-service-role",
    "proxy-server"         : "nginx"
}